setup.py
moke_config/__init__.py
moke_config/configbase.py
moke_config.egg-info/PKG-INFO
moke_config.egg-info/SOURCES.txt
moke_config.egg-info/dependency_links.txt
moke_config.egg-info/top_level.txt