Metadata-Version: 1.1
Name: moke-config
Version: 0.2.0
Summary: This is a config utility for tree structure, PyCharm complement and overriding by dictionary.
Home-page: https://github.com/mokemokechicken/moke_config
Author: mokemokechicken
Author-email: mokemokechicken@gmail.com
License: MIT
Keywords: config PyCharm utility
Platform: UNKNOWN
Classifier: Programming Language :: Python :: 3
Classifier: Topic :: Utilities
